kipsum/__init__.py
kipsum/kipsum.py
kipsum/sources/yechan.json
kipsum-1.0.0.dist-info/WHEEL
kipsum-1.0.0.dist-info/METADATA
kipsum-1.0.0.dist-info/RECORD
