Metadata-Version: 2.1
Name: kipsum
Version: 1.0.0
Summary: Korean lorem ipsum generator
Home-page: https://github.com/jrog612/kipsum
License: MIT
Author: jrog612
Author-email: wnrhd114@gmail.com
Requires-Python: >=3.8,<4.0
Classifier: License :: OSI Approved :: MIT License
Classifier: Programming Language :: Python :: 3
Classifier: Programming Language :: Python :: 3.8
Classifier: Programming Language :: Python :: 3.9
Classifier: Programming Language :: Python :: 3.10
Classifier: Programming Language :: Python :: 3.11
Project-URL: Repository, https://github.com/jrog612/kipsum
